ccorp/ruamel/yaml/include/__init__.py
ccorp_yaml_include-0.0.2.dist-info/LICENSE
ccorp_yaml_include-0.0.2.dist-info/METADATA
ccorp_yaml_include-0.0.2.dist-info/WHEEL
ccorp_yaml_include-0.0.2.dist-info/top_level.txt
ccorp_yaml_include-0.0.2.dist-info/RECORD
