Metadata-Version: 2.1
Name: ccorp-yaml-include
Version: 0.0.2
Summary: An extension of ruamel.yaml to support including aliases
Home-page: UNKNOWN
Author: Tristan Sweeney
Author-email: tristan.sweeney@cambridgeconsultants.com
License: UNKNOWN
Platform: UNKNOWN
Classifier: Programming Language :: Python :: 3
Classifier: License :: OSI Approved :: MIT License
Classifier: Operating System :: OS Independent
Requires-Dist: ruamel.yaml
